{
    "1.docx": [
        "акт забраковки",
        "лаборант",
        "влажность",
        "зольность",
        "фракция",
        "начальник производства",
        "акт списания",
        "бухгалтерия",
        "количество бегов",
        "количество тонн",
        "причина брака",
        "решение по фракции",
        "согласование с начальником производства",
        "контроль качества",
        "отчетность",
        "рекламированный продукт"
    ],
    "02.04 - 08.04.docx": [
        "боевой план",
        "руководитель отделения",
        "статистики",
        "квота",
        "выполнение квоты",
        "инспекция отчетов",
        "координация с руководителем",
        "собрание персонала",
        "найм",
        "обучение",
        "мотивация",
        "регламент",
        "программа по устранению отклонений",
        "проект по 13-й зарплате",
        "кадровые решения",
        "эффективность сотрудников",
        "планирование"
    ],
    "2. Цель поста.docx": [
        "цель поста",
        "ценный конечный продукт",
        "описание задач",
        "целевая аудитория",
        "основные функции",
        "результаты работы",
        "ключевые показатели эффективности",
        "стратегические цели",
        "операционные задачи",
        "управление персоналом",
        "внутренние процессы",
        "координация задач",
        "ежедневные задачи",
        "основные обязанности",
        "оценка эффективности"
    ],
    "3. Ценный конечный продукт поста ЦКП.docx": [
        "ценный конечный продукт",
        "ожидаемые результаты",
        "основные обязанности",
        "контрольные точки",
        "оценка эффективности",
        "конечный результат",
        "показатели достижения",
        "регламенты",
        "оптимизация работы",
        "контроль исполнения",
        "достижение целей",
        "результаты труда",
        "операционные показатели",
        "производственные задачи"
    ],
    "04.06 - 10.06.24.docx": [
        "боевой план",
        "руководитель",
        "количество сотрудников с выполненной квотой",
        "ежедневная координация",
        "отчет по выполнению квоты",
        "собрание персонала",
        "совет по качеству",
        "план подразделения",
        "рекомендательный совет",
        "найм",
        "обучение",
        "программы и проекты",
        "корпоративное обучение",
        "ротация сотрудников",
        "взаимодействие с владельцем",
        "мотивационные программы",
        "координация действий",
        "производственные показатели",
        "коммуникации с персоналом",
        "финансовые отчеты"
    ],
    "04.06.24 - 10.06.24г БП РО 2 МП Лахно Ярослав.docx": [
        "боевой план",
        "руководитель",
        "валовая прибыль",
        "валовый доход",
        "количество заказов",
        "клиенты категории Y",
        "координация с руководителем",
        "статистики",
        "отчет по обучению",
        "совет по качеству",
        "план подразделения",
        "привлечение клиентов",
        "мониторинг тендеров",
        "коммерческие предложения",
        "производственные задачи",
        "координация с начальником производства",
        "план поставок",
        "подготовка отчетов",
        "переговоры с клиентами",
        "анализ конкурентов",
        "оптимизация затрат"
    ],
    "04.06.24-10.06.24.docx": [
        "боевой план",
        "менеджер секции",
        "статистики",
        "количество доставленного товара",
        "координация с руководителем",
        "отчет по выполнению квоты",
        "контроль узких мест",
        "сведение взаиморасчетов",
        "производство мелиоративное",
        "отгрузка материалов",
        "управление персоналом",
        "задачи по обучению",
        "планирование ресурсов",
        "производственные процессы",
        "регламент работ",
        "координация работы с подрядчиками",
        "оценка рисков",
        "инвентаризация",
        "финансовое планирование"
    ],
    "4. Идеальная картина работы на данном посту.docx": [
        "идеальная картина работы",
        "эффективность работы",
        "контроль качества",
        "управление процессами",
        "организация труда",
        "улучшение результатов",
        "стандарты выполнения",
        "постановка задач",
        "оценка производительности",
        "внедрение стандартов",
        "оптимизация работы",
        "взаимодействие с коллегами",
        "результативность",
        "координация проектов",
        "достижение целей"
    ],
    "5. Приоритеты в организации работы на данном посту.docx": [
        "приоритеты работы",
        "организация труда",
        "распределение обязанностей",
        "повышение производительности",
        "улучшение процессов",
        "управление задачами",
        "ключевые направления",
        "планирование задач",
        "контроль выполнения",
        "координация с руководством",
        "работа с персоналом",
        "внедрение нововведений",
        "оптимизация времени",
        "эффективность выполнения",
        "постановка целей"
    ],
    "6. Положение поста на орг.схеме.docx": [
        "положение поста",
        "организационная схема",
        "структура подразделений",
        "взаимодействие отделов",
        "роли и обязанности",
        "корпоративная иерархия",
        "назначение обязанностей",
        "взаимодействие с коллегами",
        "управление процессами",
        "координация действий",
        "ответственность за результаты",
        "постановка задач",
        "управление ресурсами",
        "функциональная структура",
        "командная работа"
    ],
    "7. Экземпляр орг.схемы отделения, к которому относится пост.docx": [
        "организационная схема",
        "экземпляр схемы",
        "структура отделения",
        "распределение обязанностей",
        "подразделения",
        "коммуникационные линии",
        "иерархия",
        "отделения",
        "взаимодействие",
        "структурные подразделения",
        "взаимодействие отделов",
        "пост в структуре",
        "организационные процессы"
    ],
    "08.08-21.08.23.docx": [
        "боевой план",
        "регулярные задачи",
        "статистики",
        "действия на неделю",
        "планирование",
        "управление персоналом",
        "система отчетности",
        "контроль выполнения задач",
        "мотивация сотрудников",
        "координация",
        "управление производством",
        "документы по коммерческой тайне",
        "материальная ответственность",
        "работа с ИТ-системами",
        "освоение корпоративных инструментов",
        "производственные планы",
        "обратная связь",
        "координация с руководством"
    ],
    "8b. Обязанности отделения.docx": [
        "обязанности отделения",
        "основные функции",
        "распределение обязанностей",
        "контроль качества",
        "регламенты работы",
        "ответственность сотрудников",
        "организация работы",
        "планирование задач",
        "взаимодействие между отделами",
        "управление процессами",
        "ежедневные задачи",
        "работа с документами"
    ],
    "8c. Регулярные действия.docx": [
        "регулярные действия",
        "план работы",
        "еженедельные задачи",
        "ежемесячные задачи",
        "годовой план",
        "распределение времени",
        "продукты по задачам",
        "дневное планирование",
        "контроль выполнения",
        "операционные задачи",
        "управление задачами",
        "координация действий"
    ],
    "8d. Примеры документов и бланков, которые относятся к получению продукта поста.docx": [
        "документы",
        "бланки",
        "получение продукта",
        "формы отчетности",
        "регистрационные документы",
        "рабочие бланки",
        "шаблоны документов",
        "документы по продукту",
        "справочные материалы",
        "производственные документы",
        "отчетные формы"
    ],
    "8e. Инструменты, необходимые для производства ЦКП.docx": [
        "инструменты",
        "производство ЦКП",
        "ноутбук",
        "мышка",
        "рабочее место",
        "система 3х корзин",
        "коммуникационный центр",
        "информационный центр",
        "программа Оргстак",
        "Битрикс",
        "1С Медок",
        "электронная почта",
        "ZOOM",
        "Телеграмм",
        "группы в Телеграмме",
        "Богушбук",
        "координации",
        "статистики",
        "шляпа поста",
        "бланки документов"
    ],
    "8f. Статистики поста.docx": [
        "статистики поста",
        "руководитель отделения",
        "квалификация",
        "отчетность",
        "ключевые показатели",
        "метрики эффективности",
        "оценка производительности",
        "регулярные показатели",
        "план-факт анализ",
        "управление статистиками",
        "оперативная отчетность",
        "мониторинг"
    ],
    "8а. Основные обязанности на посту.docx": [
        "основные обязанности",
        "обязанности на посту",
        "ключевые задачи",
        "должностные инструкции",
        "управление задачами",
        "выполнение обязанностей",
        "контроль результатов",
        "ответственность за задачи",
        "ежедневные обязанности",
        "организация работы",
        "регламенты работы"
    ],
    "07.05.24 - 13.05.24г БП РО2 МП Лахно Ярослав.docx": [
        "боевой план",
        "руководитель отдела",
        "валовая прибыль",
        "валовый доход",
        "количество заказов",
        "клиенты категории Y",
        "координация с подчиненными",
        "ежедневная координация",
        "еженедельные статистики",
        "планирование",
        "производственные задачи",
        "мониторинг тендеров",
        "обратная связь с клиентами",
        "переговоры с клиентами",
        "повышение цен",
        "производственные отчеты"
    ],
    "07.05.24-13.05.24.docx": [
        "боевой план",
        "менеджер секции",
        "статистики",
        "количество доставленного товара",
        "координация с руководителем",
        "отчет по выполнению квоты",
        "контроль узких мест",
        "сведение взаиморасчетов",
        "управление производством",
        "отгрузка материалов",
        "планирование ресурсов",
        "регламент работ",
        "управление персоналом",
        "координация работы с подрядчиками"
    ],
    "12. Подборка письменных материалов, указанных в контрольном листе, плюс любые книги или руководства по использованию оборудования.docx": [
        "письменные материалы",
        "контрольный лист",
        "руководства по оборудованию",
        "использование оборудования",
        "учебные материалы",
        "документы по обучению",
        "книги и руководства",
        "инструкции по оборудованию",
        "регламенты и стандарты",
        "рекомендации по использованию",
        "производственные инструкции",
        "документация по безопасности",
        "технические руководства",
        "производственные процессы",
        "контрольные материалы"
    ],
    "13. Схема потоков частиц, отражающая, какие частицы приходят на пост, какие изменения необходимо производить с этими частицами, и куда их потом направлять.docx": [
        "схема потоков частиц",
        "изменения частиц",
        "потоки частиц",
        "управление потоками",
        "документы по изменениям",
        "контрольные точки",
        "боевой план",
        "финансовое планирование",
        "зарплатный файл",
        "отчет по квоте",
        "зрс",
        "заказ на приобретение",
        "начисление зарплаты",
        "сообщения телеграмм",
        "программа по развитию",
        "протокол совета",
        "проверочные списки",
        "документы по взаимодействию",
        "отчетность",
        "курсы и семинары",
        "обратная связь"
    ],
    "14.05.24 - 20.05.24г БП РО2 МП Лахно Ярослав.docx": [
        "боевой план",
        "руководитель отдела",
        "валовая прибыль",
        "валовый доход",
        "количество заказов",
        "клиенты категории Y",
        "ежедневная координация",
        "еженедельные статистики",
        "планирование задач",
        "мониторинг тендеров",
        "обратная связь с клиентами",
        "переговоры с клиентами",
        "производственные задачи",
        "отчеты по выполнению",
        "финансовое управление",
        "контроль выполнения",
        "управление проектами",
        "координация с подчиненными",
        "управление ресурсами",
        "анализ продаж",
        "финансовые показатели"
    ],
    "09.04 - 15.04.docx": [
        "боевой план",
        "руководитель отделения",
        "статистики",
        "выполнение квоты",
        "ежедневная инспекция",
        "координация с руководителем",
        "собрание персонала",
        "бизнес процессы",
        "регламент по оплате труда",
        "найм сотрудников",
        "конференция по HR",
        "еженедельные отчеты",
        "мониторинг производственных показателей",
        "анализ эффективности",
        "участие в совещаниях",
        "контроль за выполнением задач",
        "отчетность по квоте",
        "мотивация персонала",
        "управление ресурсами",
        "планирование производства"
    ],
    "09.04.24 - 15.04.24г БП РО 2 МП Лахно Ярослав.docx": [
        "боевой план",
        "менеджер секции",
        "статистики",
        "валовая прибыль",
        "валовый доход",
        "ежедневная координация",
        "еженедельные статистики",
        "обратная связь",
        "привлечение клиентов",
        "переговоры с клиентами",
        "планирование задач",
        "управление заказами",
        "финансовое планирование",
        "производственные отчеты",
        "мониторинг клиентов",
        "управление контрактами",
        "координация работы",
        "контроль выполнения",
        "управление персоналом",
        "коммерческие предложения"
    ],
    "09.04.24-15.04.24.docx": [
        "боевой план",
        "менеджер секции",
        "статистики",
        "выполнение квоты",
        "координация с руководителем",
        "подготовка финансовых заявок",
        "взаиморасчеты с поставщиками",
        "координация работы",
        "управление персоналом",
        "контроль узких мест",
        "управление проектами",
        "планирование задач",
        "анализ производительности",
        "ежедневные отчеты",
        "производственные процессы",
        "мониторинг поставок",
        "финансовое управление",
        "собрание персонала",
        "взаимодействие с подрядчиками",
        "подготовка отчетности"
    ],
    "09.08.22-15.08.22.docx": [
        "боевой план",
        "менеджер секции",
        "доставка товаров",
        "координация с руководителем",
        "статистики",
        "финансовые заявки",
        "взаиморасчеты",
        "обратная связь с клиентами",
        "производственные задачи",
        "найм сотрудников",
        "управление заказами",
        "еженедельные отчеты",
        "контроль качества",
        "анализ эффективности",
        "планирование производства",
        "координация с подчиненными",
        "мониторинг производственных показателей",
        "регламенты работы",
        "взаимодействие с клиентами",
        "собрания и совещания"
    ],
    "9. Инструкции по выполнению действий на посту.docx": [
        "инструкции по выполнению",
        "действия на посту",
        "реестр документов",
        "ссылки на гугл сайт",
        "оргполитики",
        "руководства",
        "рекомендации по действиям",
        "процедуры",
        "регламенты",
        "операционные инструкции",
        "управление задачами",
        "документация по посту",
        "действия по стандартам",
        "выполнение задач",
        "контрольные списки",
        "документы по управлению",
        "рекомендации по оптимизации",
        "ежедневные задачи",
        "управление проектами",
        "контроль выполнения"
    ],
    "10. Успешные действия и типичные ошибки.docx": [
        "успешные действия",
        "типичные ошибки",
        "рекомендации",
        "анализ ошибок",
        "советы по улучшению",
        "оптимизация работы",
        "эффективные методы",
        "корректировка ошибок",
        "достижение целей",
        "ошибки в управлении",
        "управление задачами",
        "ошибки в коммуникации",
        "регламенты по работе",
        "управление проектами",
        "анализ эффективности",
        "методы улучшения",
        "управление ресурсами",
        "оценка результатов",
        "производственные задачи",
        "контроль выполнения"
    ],
    "11. Контрольный лист для изучения всех инструктивных писем, советов, руководств, книг и для проведения упражнений, относящихся к данному посту.docx": [
        "контрольный лист",
        "инструктивные письма",
        "советы",
        "руководства",
        "книги",
        "упражнения по посту",
        "документы по обучению",
        "проверочные списки",
        "учебные материалы",
        "рекомендации по обучению",
        "инструкции по выполнению",
        "руководства по действиям",
        "управление задачами",
        "рекомендации по оптимизации",
        "стандарты выполнения",
        "оценка эффективности",
        "управление процессами",
        "документы по управлению",
        "регламенты работы",
        "управление ресурсами"
    ],
    "21.05.24-27.05.24.docx": [
        "боевой план",
        "менеджер секции",
        "статистики",
        "выполнение квоты",
        "координация с руководителем",
        "еженедельные отчеты",
        "план на неделю",
        "подготовка финансовых заявок",
        "обратная связь",
        "взаиморасчеты с поставщиками",
        "контроль узких мест",
        "управление ресурсами",
        "планирование производства",
        "мониторинг эффективности",
        "производственные задачи",
        "отгрузка материалов",
        "обеспечение сырьем",
        "взаимодействие с клиентами",
        "управление проектами"
    ],
    "21.06 - 27.06.21г БП РО 72 МП Лахно Ярослав.docx": [
        "боевой план",
        "менеджер секции",
        "статистики",
        "валовая прибыль",
        "валовый доход",
        "заказы на производство",
        "ежедневная координация",
        "план на неделю",
        "финансовые заявки",
        "сопутствующие товары",
        "переговоры с клиентами",
        "отправка образцов",
        "определение места отгрузки",
        "подтвержденные заказы",
        "производственные задачи",
        "взаимодействие с партнерами",
        "управление проектами"
    ],
    "23.04.24 - 29.04.24г БП РО 2 МП Лахно Ярослав.docx": [
        "боевой план",
        "менеджер секции",
        "статистики",
        "координация с руководителем",
        "план на неделю",
        "финансовые заявки",
        "управление заказами",
        "планирование продаж",
        "мониторинг клиентов",
        "привлечение новых заказов",
        "возврат клиентов",
        "переговоры по ценам",
        "мониторинг тендеров",
        "управление проектами",
        "контроль выполнения задач",
        "производственные задачи",
        "отгрузка материалов",
        "взаимодействие с клиентами"
    ],
    "23.04.24-29.04.24.docx": [
        "боевой план",
        "руководитель секции",
        "статистики",
        "координация с руководителем",
        "еженедельные отчеты",
        "план на неделю",
        "финансовые отчеты",
        "управление заказами",
        "взаиморасчеты",
        "отгрузка продукции",
        "мониторинг клиентов",
        "контроль выполнения",
        "производственные задачи",
        "управление ресурсами"
    ],
    "28.05 - 03.06.24.docx": [
        "боевой план",
        "руководитель отделения",
        "статистики",
        "ежедневная координация",
        "план на неделю",
        "еженедельные отчеты",
        "планирование задач",
        "подготовка финансовых заявок",
        "участие в совещаниях",
        "обратная связь с подчиненными",
        "управление ресурсами",
        "мониторинг эффективности",
        "взаимодействие с отделами",
        "координация работы",
        "обучение персонала",
        "отгрузка материалов",
        "управление проектами",
        "контроль выполнения"
    ],
    "14.05.24-20.05.24.docx": [
        "боевой план",
        "менеджер секции",
        "статистики",
        "координация с руководителем",
        "еженедельные отчеты",
        "план на неделю",
        "подготовка финансовых заявок",
        "взаиморасчеты с поставщиками",
        "управление проектами",
        "производственные задачи",
        "мониторинг эффективности",
        "отгрузка материалов",
        "обеспечение сырьем",
        "взаимодействие с клиентами",
        "контроль выполнения задач",
        "управление ресурсами"
    ],
    "16.04.24 - 22.04.24г БП РО 2 МП Лахно Ярослав.docx": [
        "боевой план",
        "менеджер секции",
        "статистики",
        "координация с руководителем",
        "план на неделю",
        "управление заказами",
        "финансовые заявки",
        "взаиморасчеты",
        "производственные задачи",
        "управление проектами",
        "взаимодействие с клиентами",
        "мониторинг эффективности",
        "контроль выполнения задач",
        "отгрузка материалов",
        "обеспечение сырьем",
        "планирование производства"
    ],
    "16.04.24-22.04.24_.docx": [
        "боевой план",
        "менеджер секции",
        "статистики",
        "координация с руководителем",
        "еженедельные отчеты",
        "управление заказами",
        "подготовка финансовых заявок",
        "отгрузка материалов",
        "мониторинг эффективности",
        "взаиморасчеты",
        "контроль узких мест",
        "управление проектами",
        "взаимодействие с партнерами"
    ],
    "21.05 - 27.05.24.docx": [
        "боевой план",
        "руководитель секции",
        "статистики",
        "план на неделю",
        "координация с руководителем",
        "еженедельные отчеты",
        "управление заказами",
        "подготовка отчетности",
        "контроль выполнения",
        "взаимодействие с отделами",
        "управление проектами",
        "отгрузка продукции",
        "обеспечение сырьем",
        "производственные задачи"
    ],
    "21.05.24 - 27.05.24г БП РО 2 МП Лахно Ярослав.docx": [
        "боевой план",
        "менеджер секции",
        "статистики",
        "еженедельные отчеты",
        "координация с руководителем",
        "управление заказами",
        "план на неделю",
        "управление ресурсами",
        "подготовка финансовых заявок",
        "отгрузка материалов",
        "мониторинг эффективности",
        "контроль выполнения задач",
        "производственные задачи"
    ],
    "2020_02_20_И_Формирование_Заказа_покупателя_в_1_С_Известняк.docx": [
        "формирование заказа",
        "заказ покупателя",
        "1С",
        "документы",
        "менеджер по продажам",
        "данные клиента",
        "товарная накладная",
        "планирование",
        "согласование заказа",
        "отгрузка товара",
        "реализация продукции",
        "ведение отчетности",
        "учет остатков",
        "контроль заказов",
        "заполнение формы",
        "данные по заказу",
        "интерфейс 1С",
        "подготовка документов",
        "настройка шаблонов",
        "сопроводительные документы"
    ],
    "2020_06_15_ИП_Правила_по_работе_с_перевозчиками.docx": [
        "правила работы с перевозчиками",
        "наемный транспорт",
        "документы на автомобиль",
        "загрузка",
        "проверка веса",
        "целостность упаковки",
        "разгрузка",
        "ЖД станция",
        "логистика",
        "контроль маршрута",
        "ответственность водителя",
        "передача документов",
        "сопроводительные документы",
        "время прибытия",
        "маршрут следования",
        "обратная связь с логистом",
        "ситуации в пути",
        "взаимодействие с клиентом",
        "контроль груза",
        "соблюдение правил"
    ],
    "2020_08_26_Инструкция_Создание_Отчета_о_запасах_производства.docx": [
        "создание отчета",
        "запасы производства",
        "1С",
        "планирование",
        "готовая продукция",
        "остатки продукции",
        "формирование отчета",
        "поля для заполнения",
        "структурная единица",
        "данные для отчетности",
        "анализ остатков",
        "управление запасами",
        "производственные данные",
        "контроль объемов",
        "ведение отчетности",
        "подготовка данных",
        "взаимодействие с отделами",
        "учет производственной продукции",
        "согласование данных",
        "использование системы 1С"
    ],
    "2020_09_01_Конкурентные_преимущества_сотрудничества_с_компанией.docx": [
        "конкурентные преимущества",
        "сотрудничество с компанией",
        "успешная работа",
        "диверсификация производства",
        "логистические услуги",
        "качество продукции",
        "условия оплаты",
        "изготовление под заказ",
        "оперативность выполнения",
        "профессионализм персонала",
        "награды компании",
        "сертифицированная продукция",
        "удовлетворение потребностей клиента",
        "гибкость условий",
        "экспериментальные партии",
        "технические требования",
        "качество сырья",
        "клиентская поддержка",
        "долгосрочное сотрудничество",
        "надежность партнерства"
    ],
    "2020_09_02_Инструкция_Способы_поиска_нового_клиента.docx": [
        "поиск нового клиента",
        "менеджер по продажам",
        "сферы применения продукции",
        "поиск через интернет",
        "СМИ",
        "базы данных",
        "обзвон",
        "выставки",
        "рекомендации",
        "партнерские программы",
        "расширение клиентской базы",
        "целевые клиенты",
        "сегментация рынка",
        "анализ конкурентов",
        "контактная информация",
        "работа с ЛПР",
        "переговоры с клиентами",
        "профильные мероприятия",
        "фиксирование данных",
        "система CRM"
    ],
    "28.05.24 - 03.06.24г БП РО 2 МП Лахно Ярослав.docx": [
        "боевой план",
        "менеджер секции",
        "статистики",
        "выполнение квоты",
        "координация с руководителем",
        "еженедельные отчеты",
        "план на неделю",
        "финансовые заявки",
        "отгрузка продукции",
        "взаиморасчеты с поставщиками",
        "управление проектами",
        "контроль выполнения задач",
        "обеспечение сырьем",
        "взаимодействие с клиентами",
        "мониторинг эффективности",
        "производственные задачи",
        "согласование поставок",
        "анализ выполнения",
        "управление ресурсами",
        "ежедневная координация"
    ],
    "28.05.24-03.06.24.docx": [
        "боевой план",
        "менеджер секции",
        "статистики",
        "план на неделю",
        "подготовка финансовых заявок",
        "управление заказами",
        "отгрузка материалов",
        "мониторинг клиентов",
        "взаиморасчеты",
        "координация с отделами",
        "контроль выполнения задач",
        "управление проектами",
        "производственные показатели",
        "контроль узких мест",
        "работа с поставщиками",
        "оптимизация процессов",
        "корректировка планов",
        "финансовая отчетность",
        "ежедневные задачи",
        "собрания персонала"
    ],
    "30.04.24-06.05.24.docx": [
        "боевой план",
        "менеджер секции",
        "статистики",
        "координация с руководителем",
        "еженедельные отчеты",
        "план на неделю",
        "подготовка финансовых заявок",
        "управление проектами",
        "производственные задачи",
        "мониторинг эффективности",
        "отгрузка материалов",
        "взаимодействие с клиентами",
        "контроль выполнения задач",
        "управление ресурсами",
        "обратная связь",
        "регулярные задачи",
        "планирование действий",
        "контроль заказов",
        "подведение итогов",
        "согласование с подчиненными"
    ],
    "30.04.24-06.05.24г БП РО 2 МП Лахно Ярослав.docx": [
        "боевой план",
        "руководитель отдела",
        "статистики",
        "координация с руководителем",
        "еженедельные отчеты",
        "управление заказами",
        "план на неделю",
        "подготовка финансовых заявок",
        "отгрузка материалов",
        "управление проектами",
        "контроль выполнения задач",
        "взаимодействие с клиентами",
        "мониторинг эффективности",
        "управление ресурсами",
        "подготовка отчетов",
        "ежедневная координация",
        "составление графиков",
        "работа с подчиненными",
        "согласование задач",
        "подготовка предложений"
    ],
    "2015-04-06 Регламент по использованию оргсхемы -ООО -Компания ВБА. Направление Известняки.docx": [
        "регламент по использованию оргсхемы",
        "структура компании",
        "организационные схемы",
        "распределение обязанностей",
        "взаимодействие отделов",
        "иерархия",
        "подразделения",
        "оргструктура",
        "коммуникации",
        "корпоративные стандарты",
        "организационная структура",
        "взаимодействие с руководством",
        "управление процессами",
        "контроль исполнения",
        "передача полномочий",
        "назначение ответственных",
        "описание должностей",
        "регламент взаимодействия",
        "корпоративная культура",
        "соблюдение стандартов"
    ],
    "Акт брака продукции.docx": [
        "акт забраковки",
        "лаборант",
        "фракция",
        "влажность",
        "зольность",
        "бригадир",
        "начальник производства",
        "причина брака",
        "решение по фракции",
        "акт списания",
        "бухгалтерия",
        "контроль качества",
        "документы по браку",
        "списание продукции",
        "анализ брака",
        "производственный учет",
        "управление качеством",
        "отчетность",
        "документация"
    ],
    "БП 07.05-13.05.2024 Бухгалтер по первичной документации.docx": [
        "боевой план",
        "бухгалтер по первичной документации",
        "статистики",
        "план на день",
        "ежедневная координация",
        "обработка входящих писем",
        "планирование задач",
        "финансовые заявки",
        "приходные документы",
        "расходные документы",
        "разнос выписок",
        "документация",
        "сверка данных",
        "отчетность в 1С",
        "управленческий учет",
        "регулярные действия",
        "подготовка документов",
        "обучение",
        "взаимодействие с коллегами",
        "папка должности"
    ],
    "БП 1.docx": [
        "боевой план",
        "стажер",
        "статистики",
        "производственные задачи",
        "план на день",
        "ежедневная координация",
        "инвентаризация",
        "охрана труда",
        "дисциплина на производстве",
        "закупка материалов",
        "планирование производства",
        "управление задачами",
        "отчетность",
        "производственные процессы",
        "управление оборудованием",
        "координация с руководством",
        "контроль качества",
        "планирование обучения",
        "внедрение в должность",
        "анализ выполнения"
    ],
    "БП 04.06-10.06.2024 Бухгалтер по первичной документации.docx": [
        "боевой план",
        "бухгалтер по первичной документации",
        "статистики",
        "план на день",
        "ежедневная координация",
        "обработка входящих писем",
        "планирование задач",
        "финансовые заявки",
        "приходные документы",
        "расходные документы",
        "разнос выписок",
        "документация",
        "сверка данных",
        "отчетность в 1С",
        "управленческий учет",
        "регулярные действия",
        "подготовка документов",
        "обучение",
        "взаимодействие с коллегами",
        "папка должности"
    ],
    "БП 21.05-27.05.2024 Алексеева Светлана.docx": [
        "боевой план",
        "бухгалтер по первичной документации",
        "статистики",
        "план на день",
        "ежедневная координация",
        "обработка входящих писем",
        "планирование задач",
        "финансовые заявки",
        "приходные документы",
        "расходные документы",
        "разнос выписок",
        "документация",
        "сверка данных",
        "отчетность в 1С",
        "управленческий учет",
        "регулярные действия",
        "подготовка документов",
        "обучение",
        "взаимодействие с коллегами",
        "папка должности"
    ],
    "БП 16.04 - 22.04.24.docx": [
        "боевой план",
        "руководитель отделения",
        "статистики",
        "план на неделю",
        "координация с руководителем",
        "инспекция отчетов",
        "выполнение квоты",
        "собрание персонала",
        "инспекция планов",
        "совет по качеству",
        "рекомендательный совет",
        "найм сотрудников",
        "управление персоналом",
        "введение в должность",
        "контроль выполнения задач",
        "регламенты компании",
        "управление проектами",
        "обучение сотрудников",
        "финансовое планирование",
        "управление ресурсами"
    ],
    "БП 20.docx": [
        "боевой план",
        "начальник отдела",
        "статистики",
        "план на неделю",
        "координация с руководителем",
        "финансовые показатели",
        "заказы на производство",
        "развитие клиентов",
        "анализ звонков",
        "управление проектами",
        "контроль выполнения задач",
        "еженедельные отчеты",
        "подготовка финансовых заявок",
        "участие в совещаниях",
        "обучение",
        "управление заказами",
        "контроль качества",
        "планирование производства",
        "мониторинг клиентов",
        "развитие рынков сбыта"
    ],
    "БП 07.05 - 13.05.docx": [
        "боевой план",
        "руководитель отделения",
        "статистики",
        "план на неделю",
        "ежедневная координация",
        "входящая коммуникация",
        "планирование задач",
        "собрание персонала",
        "совет по качеству",
        "рекомендательный совет",
        "управление проектами",
        "финансовое планирование",
        "отчетность",
        "контроль выполнения",
        "подготовка финансовых заявок",
        "инспекция задач",
        "наем сотрудников",
        "обучение персонала",
        "введение в должность",
        "корректировка регламентов"
    ],
    "БП 28.05-03.06.2024 Бухгалтера по первичной документации": [
        "боевой план на неделю",
        "бухгалтер по первичной документации",
        "обработка входящей коммуникации",
        "план на день",
        "координация с руководителем",
        "подведение еженедельных статистик",
        "отчёт по выполнению квоты",
        "финансовые заявки",
        "участие в общем собрании",
        "разнесение выписок в 1С",
        "проведение приходных документов",
        "проведение расходных документов",
        "раскладка документов по регистрам",
        "загрузка входящих НН",
        "сверка НН для декларации",
        "составление реестра",
        "подготовка документов для разблокировки НН",
        "проектные задачи",
        "обучение сотрудников",
        "инструкция по работе с google-сайтом",
        "дополнение папки должности"
    ],
    "БП 30.04-06.05.2024 Бухгалтер по первичной документации": [
        "боевой план на неделю",
        "бухгалтер по первичной документации",
        "обработка входящей коммуникации",
        "составление плана на день",
        "координация с руководителем",
        "подведение еженедельных статистик",
        "отчёт по выполнению квоты",
        "финансовые заявки",
        "участие в общем собрании",
        "разнесение выписок в 1С",
        "проведение приходных документов",
        "проведение расходных документов",
        "загрузка входящих НН",
        "сверка НН для декларации",
        "составление реестра",
        "обучение по программе",
        "дополнение папки должности"
    ],
    "БП Алексеева Светлана 09.04-15.04.24": [
        "боевой план на неделю",
        "бухгалтер по первичной документации",
        "стажёр",
        "обработка входящей коммуникации",
        "план на день",
        "координация с руководителем",
        "подведение еженедельных статистик",
        "составление плана на неделю",
        "подписание финансовых заявок",
        "участие в общем собрании",
        "служебные записки",
        "разнесение выписок в 1С",
        "проведение приходных документов",
        "проведение расходных документов",
        "сверка НН для декларации",
        "обучение по видео-курсу",
        "регламент по статистикам",
        "ознакомление с справочником статистик"
    ],
    "БП Алексеева Светлана 16.04-22.04.24": [
        "боевой план на неделю",
        "бухгалтер по первичной документации",
        "стажёр",
        "обработка входящей коммуникации",
        "план на день",
        "координация с руководителем",
        "подведение еженедельных статистик",
        "составление плана на неделю",
        "подписание финансовых заявок",
        "участие в общем собрании",
        "служебные записки",
        "разнесение выписок в 1С",
        "загрузка входящих НН",
        "проведение приходных документов",
        "проведение расходных документов",
        "сверка НН для декларации",
        "обучение по видео-курсу",
        "регламент по должностным обязанностям",
        "инструкция по производственным процессам",
        "шкала компетентности"
    ],
    "БП 23.04.-29.04.24 Бухгалтер по первичной документации": [
        "боевой план на неделю",
        "бухгалтер по первичной документации",
        "стажёр",
        "обработка входящей коммуникации",
        "план на день",
        "координация с руководителем",
        "подведение еженедельных статистик",
        "составление плана на неделю",
        "подписание финансовых заявок",
        "участие в общем собрании",
        "служебные записки",
        "разнесение выписок в 1С",
        "загрузка входящих НН",
        "проведение приходных документов",
        "проведение расходных документов",
        "сверка НН для декларации",
        "изучение регламентов по учету",
        "финансовое планирование",
        "виды статусов в 1С",
        "регламент по финансовому планированию"
    ],
    "БП НО11 16.01.23-22.01.23": [
        "боевой план на две недели",
        "стажёр НО11",
        "статистики производства",
        "регулярные действия",
        "координация с руководителем",
        "утренняя координация",
        "общее собрание персонала",
        "учебные задачи",
        "курс Эйнштейн Коммуникации",
        "инвентаризация",
        "контроль выполнения задач",
        "ремонт оборудования",
        "производственные задачи",
        "собрание по ИП",
        "отчёты о производстве",
        "контроль загрузки продукции"
    ],
    "БП НО11 19.09.23-25.09.23": [
        "боевой план на неделю",
        "стажёр НО11",
        "статистики производства",
        "регулярные задачи",
        "координация с руководителем",
        "утренняя координация",
        "общее собрание персонала",
        "учебные задачи",
        "инвентаризация",
        "контроль выполнения задач",
        "ремонт оборудования",
        "производственные задачи",
        "собрание по ИП",
        "отчёты о производстве",
        "контроль загрузки продукции"
    ],
    "БП 26.03 - 01.04_.docx": [
        "боевой план на неделю",
        "руководитель отделения",
        "координация с руководителем",
        "ежедневная инспекция отчетов",
        "подведение статистик",
        "общие собрания",
        "контроль выполнения задач",
        "еженедельные инспекции",
        "обучение сотрудников",
        "управление производственными процессами",
        "управление кадровыми ресурсами"
    ],
    "БП НО11.docx": [
        "боевой план на две недели",
        "стажёр НО11",
        "статистики производства",
        "регулярные действия",
        "координация с руководителем",
        "утренняя координация",
        "общее собрание персонала",
        "учебные задачи",
        "курс Эйнштейн Коммуникации",
        "инвентаризация",
        "контроль выполнения задач",
        "ремонт оборудования",
        "производственные задачи",
        "собрание по ИП",
        "отчёты о производстве",
        "контроль загрузки продукции"
    ],
    "БП НО11_(1).docx": [
        "боевой план на две недели",
        "стажёр НО11",
        "статистики производства",
        "регулярные задачи",
        "координация с руководителем",
        "утренняя координация",
        "общее собрание персонала",
        "учебные задачи",
        "курс Эйнштейн Коммуникации",
        "инвентаризация",
        "контроль выполнения задач",
        "ремонт оборудования",
        "производственные задачи",
        "собрание по ИП",
        "отчёты о производстве",
        "контроль загрузки продукции"
    ],
    "БП НО11_(2).docx": [
        "боевой план на две недели",
        "стажёр НО11",
        "статистики производства",
        "регулярные задачи",
        "координация с руководителем",
        "утренняя координация",
        "общее собрание персонала",
        "учебные задачи",
        "курс Эйнштейн Коммуникации",
        "инвентаризация",
        "контроль выполнения задач",
        "ремонт оборудования",
        "производственные задачи",
        "собрание по ИП",
        "отчёты о производстве",
        "контроль загрузки продукции"
    ],
    "БП НО11_.docx": [
        "боевой план на две недели",
        "стажёр НО11",
        "статистики производства",
        "регулярные задачи",
        "координация с руководителем",
        "утренняя координация",
        "общее собрание персонала",
        "учебные задачи",
        "курс Эйнштейн Коммуникации",
        "инвентаризация",
        "контроль выполнения задач",
        "ремонт оборудования",
        "производственные задачи",
        "собрание по ИП",
        "отчёты о производстве",
        "контроль загрузки продукции"
    ],
    "БП НО11 29.01.31-05.02.31.docx": [
        "боевой план на две недели",
        "стажёр НО11",
        "статистики производства",
        "регулярные задачи",
        "координация с руководителем",
        "утренняя координация",
        "общее собрание персонала",
        "учебные задачи",
        "курс Эйнштейн Коммуникации",
        "инвентаризация",
        "контроль выполнения задач",
        "ремонт оборудования",
        "производственные задачи",
        "собрание по ИП",
        "отчёты о производстве",
        "контроль загрузки продукции"
    ],
    "БП НО11 29.08.23-04.09.23.docx": [
        "боевой план на две недели",
        "стажёр НО11",
        "статистики производства",
        "регулярные задачи",
        "координация с руководителем",
        "утренняя координация",
        "общее собрание персонала",
        "учебные задачи",
        "курс Эйнштейн Коммуникации",
        "инвентаризация",
        "контроль выполнения задач",
        "ремонт оборудования",
        "производственные задачи",
        "собрание по ИП",
        "отчёты о производстве",
        "контроль загрузки продукции"
    ],
    "БП1.docx": [
        "боевой план на неделю",
        "руководитель НО11 МЛ",
        "объём производства",
        "регулярные задачи",
        "координация с подчиненными",
        "ежедневный отчёт",
        "еженедельные статистики",
        "план на неделю",
        "учебные задачи",
        "заказы на приобретение",
        "общие собрания",
        "совет по качеству",
        "рекомендательный совет",
        "встреча с владельцем",
        "дополнение папки должности",
        "индивидуальная программа обучения"
    ],
    "БП2.docx": [
        "боевой план на неделю",
        "руководитель НО11 МЛ",
        "объём производства",
        "регулярные задачи",
        "координация с подчиненными",
        "ежедневный отчёт",
        "еженедельные статистики",
        "план на неделю",
        "учебные задачи",
        "заказы на приобретение",
        "общие собрания",
        "совет по качеству",
        "рекомендательный совет",
        "встреча с владельцем",
        "дополнение папки должности",
        "индивидуальная программа обучения",
        "правила получения дипломов и наград"
    ],
    "БП3 14.05-20.05.2024 Алексеева Светлана.docx": [
        "боевой план на неделю",
        "бухгалтер по первичной документации",
        "регулярные задачи",
        "проверочный список",
        "координация с руководителем",
        "отчёт по квоте",
        "план на неделю",
        "участие в собрании",
        "разнесение выписок в 1С",
        "проведение приходных документов",
        "проведение расходных документов",
        "раскладка документов по регистрам",
        "загрузка НН",
        "сверка НН",
        "разблокировка НН",
        "правила получения дипломов и наград"
    ],
    "БП НО11(1).docx": [
        "боевой план на две недели",
        "стажёр НО11",
        "статистики производства",
        "регулярные задачи",
        "координация с руководителем",
        "утренняя координация",
        "общее собрание персонала",
        "учебные задачи",
        "курс Эйнштейн Коммуникации",
        "инвентаризация",
        "контроль выполнения задач",
        "ремонт оборудования",
        "производственные задачи",
        "собрание по ИП",
        "отчёты о производстве",
        "контроль загрузки продукции",
        "планирование производства",
        "закупка материалов",
        "разъяснительные мероприятия",
        "погрузка продукции",
        "запуск мельницы",
        "анализ производства"
    ],
    "БП3 16.01-22.01.2024 Стажер Шведова Марина – копія.docx": [
        "боевой план на неделю",
        "бухгалтер по первичной документации",
        "регулярные действия",
        "координация с руководителем",
        "еженедельные статистики",
        "составление плана на неделю",
        "финансовые заявки",
        "общие собрания",
        "служебные записки",
        "разнесение выписок в 1С",
        "сверка НН",
        "проведение приходных документов",
        "архивация документов",
        "регламент по должностным папкам",
        "формула несуществования"
    ],
    "БП3.docx": [
        "боевой план на неделю",
        "координация с руководителем",
        "регулярные задачи",
        "проверочный список",
        "отчёт по квоте",
        "разнесение выписок в 1С",
        "проведение приходных документов",
        "сверка НН",
        "разблокировка НН",
        "обучение сотрудников"
    ],
    "БП4.docx": [
        "боевой план на неделю",
        "руководитель НО11 МЛ",
        "объём производства",
        "регулярные задачи",
        "координация с подчиненными",
        "ежедневный отчёт",
        "еженедельные статистики",
        "план на неделю",
        "учебные задачи",
        "заказы на приобретение",
        "общие собрания",
        "совет по качеству",
        "рекомендательный совет",
        "встреча с владельцем",
        "дополнение папки должности"
    ],
    "БП5.docx": [
        "боевой план на неделю",
        "руководитель НО11 МЛ",
        "объём производства",
        "регулярные задачи",
        "координация с подчиненными",
        "ежедневный отчёт",
        "еженедельные статистики",
        "план на неделю",
        "учебные задачи",
        "заказы на приобретение",
        "общие собрания",
        "совет по качеству",
        "рекомендательный совет",
        "встреча с владельцем",
        "дополнение папки должности",
        "индивидуальная программа обучения"
    ],
    "БП6.docx": [
        "боевой план на неделю",
        "стажёр НО11 МЛ",
        "регулярные задачи",
        "координация с руководителем",
        "ежедневный отчёт",
        "инвентаризация",
        "контроль выполнения задач",
        "план на неделю",
        "обучение сотрудников",
        "производственные задачи",
        "проект Каркас",
        "ремонт оборудования",
        "отчёты о производстве",
        "контроль загрузки продукции"
    ],
    "БП7.docx": [
        "боевой план на неделю",
        "стажёр НО11 МЛ",
        "регулярные задачи",
        "координация с руководителем",
        "ежедневный отчёт",
        "перезарядка огнетушителей",
        "планирование водоотведения",
        "проект Каркас",
        "контроль выполнения задач",
        "производственные задачи",
        "план на неделю",
        "отчёты о производстве",
        "контроль загрузки продукции"
    ],
    "БП8.docx": [
        "боевой план на неделю",
        "стажёр НО11 МЛ",
        "регулярные задачи",
        "координация с руководителем",
        "ежедневный отчёт",
        "обучение ИП",
        "контроль выполнения задач",
        "проект Каркас",
        "ремонт оборудования",
        "инвентаризация",
        "план на неделю",
        "отчёты о производстве",
        "контроль загрузки продукции"
    ],
    "БП9.docx": [
        "боевой план на неделю",
        "стажёр НО11 МЛ",
        "регулярные задачи",
        "координация с руководителем",
        "ежедневный отчёт",
        "дополнение папки должности",
        "проект Каркас",
        "контроль выполнения задач",
        "план на неделю",
        "отчёты о производстве",
        "контроль загрузки продукции"
    ],
    "БП10.docx": [
        "боевой план на неделю",
        "руководитель НО11 МЛ",
        "регулярные задачи",
        "координация с подчиненными",
        "ежедневный отчёт",
        "еженедельные статистики",
        "план на неделю",
        "заказы на приобретение",
        "общие собрания",
        "совет по качеству",
        "рекомендательный совет",
        "встреча с владельцем",
        "дополнение папки должности",
        "контроль выполнения задач",
        "ремонт оборудования",
        "отчёты о производстве",
        "контроль загрузки продукции"
    ],
    "Возврат денег (корректировка).docx": [
        "возврат денег",
        "корректировка",
        "управленка",
        "налоговые накладные",
        "медок",
        "дата возврата",
        "сумма возврата",
        "код причины",
        "приложение 2 к НН",
        "корректировка номенклатуры",
        "1С бухгалтерия",
        "заполнение полей"
    ],
    "ИЗВ 2016-04-28 Приказ О сроках проведения координаций в компании и отчетных периодах в компании направления Известняк.docx": [
        "приказ",
        "координация",
        "отчетные периоды",
        "компания ВБА",
        "регламент по координации",
        "боевые планы",
        "статистики",
        "рекомендательный совет",
        "финансовое планирование",
        "распределение маржи",
        "начисление заработной платы"
    ],
    "ИЗВ 2021-09-02 ИП Правила обеспечения вывоза готовой продукции из Каменец-Подольского 100_ 11.docx": [
        "правила вывоза готовой продукции",
        "Каменец-Подольский",
        "менеджер секции планирования",
        "менеджер секции продаж",
        "менеджер секции погрузки",
        "планирование производства",
        "движение заказа",
        "ежедневный отчет",
        "таблица Google",
        "журнал регистрации",
        "контроль погрузки",
        "взаимодействие постов"
    ],
    "известняк 2021-04-21 Приказ Об обязательном предоставлении отчета Н06 по отгрузкам.docx": [
        "приказ",
        "отчет Н06",
        "отгрузки",
        "ежедневный отчет",
        "штраф",
        "телеграмма",
        "данные по отгрузкам",
        "накопление за неделю",
        "клиенты по фракциям",
        "отчетная неделя"
    ],
    "инспекция.docx": [
        "инспекция",
        "документ",
        "проверка",
        "отчет"
    ],
    "ДОГОВІР ГПХ Гранд Помол.docx": [
        "договор ГПХ",
        "материальная ответственность",
        "сохранность ценностей",
        "инвентаризация",
        "трудовые отношения",
        "документ",
        "соглашение"
    ],
    "Договор_о_мат_ответственности_Гранд_Помол.docx": [
        "договор о материальной ответственности",
        "сохранность материальных ценностей",
        "обязанности работника",
        "взыскание убытков",
        "инвентаризация",
        "правила учета",
        "порядок списания"
    ],
    "ДОКУМЕНТ ДЛЯ ВИКИ.docx": [
        "папка должности",
        "документ",
        "задание",
        "практическое задание",
        "проект"
    ],
    "Заявка на найм бухгалтера.docx": [
        "заявка на найм",
        "описание вакансии",
        "должностные обязанности",
        "критерии оценки",
        "работа с 1С",
        "работа с Медок",
        "первичные документы",
        "сроки обработки",
        "архивация документов"
    ],
    "ИЗВ 2016-04-28 Копия Приказ О сроках проведения координаций и отчетных периодах в компании направления Известняк.docx": [
        "приказ",
        "координация",
        "отчетные периоды",
        "компания ВБА",
        "регламент по координации",
        "боевые планы",
        "статистики",
        "рекомендательный совет",
        "финансовое планирование",
        "распределение маржи",
        "начисление заработной платы"
    ],
    "Инструкии по основным обязаностям на посту_.docx": [
        "инструкции",
        "основные обязанности",
        "пост",
        "шляпа должности",
        "регламент",
        "стандартные операционные процедуры",
        "координация"
    ],
    "Инструкция - взаиморасчеты с покупателями.docx": [
        "взаиморасчеты",
        "покупатели",
        "управленка",
        "сверка",
        "акты сверки",
        "1С",
        "формирование актов",
        "отчетность"
    ],
    "Инструкция по ведению архива.docx": [
        "ведение архива",
        "первичные документы",
        "архивация",
        "управленка",
        "исходящие документы",
        "входящие документы",
        "таможенные декларации",
        "акты сверки",
        "зарплатные ведомости",
        "кассовые ордера",
        "менеджер секции архива",
        "проверка реестров"
    ],
    "ИНСТРУКЦИЯ по ведению банковских счетов в национальной валюте.docx": [
        "ведение банковских счетов",
        "национальная валюта",
        "1С Управленка",
        "Прокредитбанк",
        "банковская выписка",
        "финансовая помощь",
        "разнесение банка",
        "сверка остатков"
    ],
    "Инструкция по работе с налоговым кредитом.docx": [
        "налоговый кредит",
        "сверка НН",
        "регистрация налоговых накладных",
        "1С",
        "Медок",
        "выгрузка данных",
        "реестр",
        "налогоплательщик"
    ],
    "Инструкция по фин. заявке.docx": [
        "финансовая заявка",
        "1С Управленка",
        "финансовое планирование",
        "заказ на приобретение",
        "маржинальная прибыль",
        "премирование",
        "платежное поручение",
        "срок оплаты"
    ],
    "Инструкция_ Введеня даних працівника в електронну систему обліку робочого часу на підприємстві.docx": [
        "введение данных",
        "электронная система учета рабочего времени",
        "сканирование лица",
        "регистрация сотрудника",
        "сохранение данных",
        "пароль"
    ],
    "ИП об учете рабочего времени на производстве.docx": [
        "учет рабочего времени",
        "производство",
        "СКУД",
        "журнал прихода-ухода",
        "регистрация времени",
        "система контроля",
        "автоматический расчет ЗП"
    ],
    "МП 2016-04-28 Приказ О сроках проведения координаций и отчетных периодах в компании направления Минеральный порошок.docx": [
        "приказ",
        "координация",
        "отчетные периоды",
        "Минеральный порошок",
        "регламент по координации",
        "боевые планы",
        "статистики",
        "рекомендательный совет",
        "финансовое планирование",
        "распределение маржи",
        "начисление заработной платы"
    ],
    "Инструкции по выполнению действий на посту.docx": [
        "инструкции",
        "выполнение действий на посту",
        "организационные политики",
        "проверочный список",
        "анализ зарплаты",
        "ежедневный отчет",
        "проведение собраний",
        "награды за выполнение квоты",
        "должностные папки",
        "введение в должность",
        "чек-лист",
        "действия руководителя",
        "бронирование"
    ],
    "перенести Паспорт в медок (Порошок или Мука).docx": [
        "паспорт в Медок",
        "синхронизация Управленка с Бухгалтерией",
        "выбор паспорта",
        "подпись и отправка"
    ],
    "Перпродажа.docx": [
        "перепродажа товара",
        "ПРОМСНАБ",
        "Минеральный порошок",
        "создание документов интеркомами",
        "синхронизация с Бухгалтерией",
        "предоплата контрагента",
        "проведение РН и ПН"
    ],
    "Персональні дані гранд помол.docx": [
        "персональные данные",
        "согласие на обработку",
        "кадровое делопроизводство",
        "защита данных",
        "обновление информации"
    ],
    "Питання навчання ТЦК.docx": [
        "вопросы по мобилизации",
        "повестка",
        "ответственность за неявку",
        "отсрочка от мобилизации",
        "законные основания для выезда за границу"
    ],
    "План на неделю ИД известняки(1).docx": [
        "план на неделю",
        "исполнительный директор",
        "статистики",
        "регулярные задачи",
        "инвентаризация",
        "маржа",
        "координация с начальником производства",
        "план поставок"
    ],
    "НО8 Боевой план на 2 недели_.docx": [
        "боевой план на две недели",
        "регулярные действия",
        "задачи по обучению",
        "планирование",
        "сверка с контрагентами",
        "начисление и выплата зарплаты",
        "финансовое планирование"
    ],
    "Новая номенклатура в 1С.docx": [
        "новая номенклатура",
        "1С Управленка",
        "справочник",
        "базовая единица товара",
        "код для НН",
        "номенклатурная группа",
        "сертификат"
    ],
    "Образец коммерческого предложения на Польском_.docx": [
        "коммерческое предложение",
        "минеральный порошок",
        "логистика",
        "качество продукта",
        "доставка на время",
        "технические спецификации",
        "стоимость с НДС"
    ],
    "Образец коммерческого предложения_.docx": [
        "коммерческое предложение",
        "минеральный порошок",
        "логистика",
        "качество продукта",
        "доставка на время",
        "технические спецификации",
        "стоимость с НДС"
    ],
    "Обьявление ЕЛЕКТРИК.docx": [
        "объявление о вакансии",
        "работа электрик",
        "график работы",
        "контактный телефон"
    ],
    "План на неделю ИД известняки(7).docx": [
        "план на неделю",
        "исполнительный директор",
        "статистики",
        "регулярные задачи",
        "инвентаризация",
        "маржа",
        "координация с начальником производства",
        "план поставок",
        "согласование договоров",
        "проект Мельница МП Каменец"
    ],
    "План на неделю ИД известняки(8).docx": [
        "план на неделю",
        "исполнительный директор",
        "валовая прибыль",
        "валовый доход",
        "проверка маржи",
        "регулярные задачи",
        "обучение по индивидуальной программе",
        "проект Европа",
        "проект релокации",
        "проект запыления",
        "согласование контрактов"
    ],
    "План на неделю ИД известняки(9).docx": [
        "план на неделю",
        "исполнительный директор",
        "регулярные задачи",
        "инвентаризация",
        "согласование договоров",
        "проверка выполнения квоты",
        "проект Мельница МП Каменец",
        "координация с производством",
        "рекомендательный совет"
    ],
    "план на неделю руководителя отделения ВБА.docx": [
        "боевой план на неделю",
        "руководитель отделения",
        "регулярные задачи",
        "финансовые заявки",
        "координация с подчиненными",
        "шляпа должности",
        "обучение по программе Эйнштейн",
        "составление служебных записок",
        "подготовка к Совету по качеству"
    ],
    "План на неделю ИД известняки(2).docx": [
        "план на неделю",
        "исполнительный директор",
        "регулярные задачи",
        "инвентаризация",
        "проверка маржи",
        "координация с начальником производства",
        "проект Мельница МП Каменец",
        "согласование условий работы",
        "финансовое планирование"
    ],
    "План на неделю ИД известняки(4).docx": [
        "план на неделю",
        "исполнительный директор",
        "валовая прибыль",
        "валовый доход",
        "регулярные задачи",
        "инвентаризация",
        "координация с производством",
        "проект релокации",
        "согласование контрактов",
        "обучение по программе"
    ],
    "План на неделю ИД известняки(5).docx": [
        "план на неделю",
        "исполнительный директор",
        "регулярные задачи",
        "инвентаризация",
        "согласование договоров",
        "проверка выполнения квоты",
        "координация с производством",
        "проект релокации",
        "проект Мельница МП Каменец"
    ],
    "План на неделю ИД известняки(6).docx": [
        "план на неделю",
        "исполнительный директор",
        "регулярные задачи",
        "инвентаризация",
        "согласование договоров",
        "проверка выполнения квоты",
        "проект Мельница МП Каменец",
        "координация с производством",
        "проект Европа"
    ],
    "Признак ЭДО_.docx": [
        "ЭДО",
        "Управленка",
        "Бухгалтерия",
        "синхронизация",
        "выгрузка контрагентов",
        "карточка клиента",
        "ТТН",
        "настройка ЭДО",
        "признак ЭДО",
        "автоматизация документооборота"
    ],
    "Проверить Логистов.docx": [
        "проверка логистов",
        "анализ логистических данных",
        "логистика",
        "управление поставками",
        "координация с транспортными компаниями",
        "эффективность логистики",
        "планирование маршрутов",
        "контроль доставки",
        "логистические процессы"
    ],
    "Проверить остатки ТМЦ (если не проводится РН).docx": [
        "проверка остатков ТМЦ",
        "отчет Закупки - Запасы",
        "складские перемещения",
        "инвентаризация",
        "структурная единица",
        "РН",
        "ошибки учета",
        "корректировка запасов",
        "товарно-материальные ценности",
        "учет запасов"
    ],
    "Провести Производство в управленке_.docx": [
        "производство",
        "управленка",
        "производственный процесс",
        "табличная часть",
        "бригадная работа",
        "ИТР",
        "зарплата",
        "планирование производства",
        "введение данных",
        "выработка сотрудников",
        "спецификация"
    ],
    "Программа введения в должность бухгалтер на производстве.docx": [
        "введение в должность",
        "бухгалтер на производстве",
        "испытательный срок",
        "договор о коммерческой тайне",
        "материальная ответственность",
        "учетная запись",
        "папка должности",
        "ППФ",
        "ежедневные координации",
        "корпоративные сервисы",
        "обучение",
        "статистики",
        "планирование",
        "введение в должность",
        "организационные политики"
    ],
    "План на неделю стажера_.docx": [
        "боевой план на две недели",
        "стажер",
        "РО1 известняк",
        "ежедневная координация",
        "общие собрания",
        "курс Эйнштейн",
        "оргсхема",
        "формула несуществования",
        "коммуникация",
        "планирование",
        "введение в должность",
        "инструкции",
        "обратная связь",
        "управление задачами"
    ],
    "Плана на две недели Старичок.docx": [
        "боевой план на две недели",
        "стажер НО11",
        "ежедневная координация",
        "общие собрания",
        "технология обучения",
        "формула несуществования",
        "планирование",
        "координация с подчиненными",
        "проверка оборудования",
        "ремонтные работы",
        "производственные задачи",
        "отчетность",
        "взаимодействие с подразделениями",
        "контроль выполнения задач"
    ],
    "Плюсы компании.docx": [
        "плюсы компании",
        "производство известняка",
        "собственный отдел логистики",
        "качество продукции",
        "реакция на заказы",
        "обучение сотрудников",
        "сплоченный коллектив",
        "увеличение дохода",
        "сервис клиентам",
        "снижение себестоимости",
        "производственные мощности",
        "конкурентные преимущества"
    ],
    "Поводы для контакта с клиентом_.docx": [
        "поводы для контакта с клиентом",
        "акция",
        "новая номенклатура",
        "изменение условий",
        "увеличение мощности производства",
        "поздравления",
        "финансовые вопросы",
        "дебиторка",
        "вопросы партнерства",
        "персонализированные предложения",
        "презентации",
        "информирование клиентов",
        "изменения на рынке",
        "обратная связь от клиентов",
        "продвижение продукта"
    ],
    "Реализация в валюте.docx": [
        "реализация в валюте",
        "1С Управленка",
        "склад",
        "НДС 0%",
        "сверка суммы с ГТД",
        "пересчет валюты",
        "внесение данных"
    ],
    "Синхронизация ЭДО.docx": [
        "синхронизация ЭДО",
        "Управленка с Бухгалтерией",
        "период передачи документов",
        "юридическое лицо",
        "фильтрация по контрагентам",
        "отправка документов",
        "Медок",
        "подпись документов"
    ],
    "Создать Паспорт вручную.docx": [
        "паспорт качества",
        "управленка",
        "закупки",
        "инвойс",
        "дата производства",
        "печатные формы",
        "вписывание номенклатуры",
        "сохранение в Excel и JPG"
    ],
    "Сохранить документы из Медка (для суда).docx": [
        "сохранение документов",
        "Медок",
        "ЭЦП",
        "графическое отображение",
        "сохранение подписи",
        "документ для суда"
    ],
    "Программа введения в должность МЕНЕДЖЕР СЕКЦИИ ИНВЕНТАРИЗАЦИИ.docx": [
        "введение в должность",
        "менеджер секции инвентаризации",
        "испытательный срок",
        "папка должности",
        "инструкции",
        "координация с руководителем",
        "ежедневные статистики",
        "управление инвентаризацией"
    ],
    "Программа введения в должность но2.docx": [
        "введение в должность",
        "НО2",
        "испытательный срок",
        "памятка стажера",
        "платформа unicraft",
        "выполнение задач",
        "оценка выполнения",
        "координация с руководителем",
        "курс обучения",
        "отчетность"
    ],
    "Программа введения в должность НО8.docx": [
        "введение в должность",
        "НО8",
        "испытательный срок",
        "договор о коммерческой тайне",
        "материальная ответственность",
        "учетная запись",
        "курс Эйнштейн",
        "организующая схема",
        "планирование",
        "статистики"
    ],
    "Программа введения в должность НО9.docx": [
        "введение в должность",
        "НО9",
        "испытательный срок",
        "папка должности",
        "документы на прием",
        "учетная запись",
        "координация с руководителем",
        "ежедневные и еженедельные отчеты",
        "письменная коммуникация",
        "статистики"
    ],
    "СПИСОК ПРАЦІВНИКІВ1.docx": [
        "список сотрудников",
        "бригады",
        "бригадиры",
        "машинисты",
        "укладальники",
        "сварщики",
        "электрики",
        "охрана",
        "ИТР",
        "контактные данные",
        "должности"
    ],
    "Программа введения в должность НО11.docx": [
        "введение в должность",
        "НО11",
        "испытательный срок",
        "договор о коммерческой тайне",
        "материальная ответственность",
        "учетная запись",
        "ежедневные координации",
        "регламент по планированию",
        "папка должности",
        "прояснение продукта и функций",
        "курс Эйнштейн",
        "статистики",
        "регулярные действия",
        "командные линии",
        "фонд оборудования"
    ],
    "Таблица Возражений клиента их прояснения и аргументация_.docx": [
        "возражения клиента",
        "прояснение возражений",
        "аргументация",
        "дорого",
        "подумаю",
        "есть поставщик",
        "работаем на прямую с карьером",
        "нет денег",
        "качество товара",
        "потребность",
        "условия оплаты",
        "доставка"
    ],
    "Универсальность сотрудников производства Каменец.docx": [
        "универсальность сотрудников",
        "производство Каменец",
        "технические навыки",
        "трактористы",
        "крановщики",
        "сварщики",
        "электрики",
        "работа на разных должностях",
        "инструктаж"
    ],
    "Что нужно знать о клиенте.docx": [
        "информация о клиенте",
        "платежеспособность",
        "география клиента",
        "лицо, принимающее решение (ЛПР)",
        "форма оплаты",
        "объемы потребления",
        "условия работы",
        "личная информация",
        "профиль клиента"
    ],
    "Экспорт в Управленке и 1С.docx": [
        "экспорт в Управленке",
        "экспорт в 1С",
        "ГТД",
        "номенклатура",
        "сверка веса",
        "тип причины 07",
        "НН",
        "РН"
    ],
    "Способы донесения информации клиентам_.docx": [
        "донесение информации",
        "клиенты",
        "почта",
        "e-mail",
        "sms",
        "мессенджеры",
        "личный звонок",
        "визитка",
        "буклет",
        "выставка",
        "конференция",
        "рекламный баннер",
        "соцсети",
        "личная встреча",
        "вебинары",
        "обучение",
        "мероприятия"
    ],
    "Сферы применения Минерального порошка и известняка.docx": [
        "сферы применения",
        "минеральный порошок",
        "известняк",
        "дорожное строительство",
        "кровельные материалы",
        "сухие строительные смеси",
        "бетон",
        "железобетонные изделия",
        "комбикорм",
        "сельское хозяйство",
        "экологически чистый продукт",
        "переработка отходов"
    ],
    "СТАРОЕ Основы которые необходимы для менеджера по продажам.docx": [
        "основы для менеджера по продажам",
        "минеральные порошки",
        "сферы применения",
        "дорожное строительство",
        "кровельные материалы",
        "сухие строительные смеси",
        "комбикорм",
        "бетон",
        "известняк",
        "доломит",
        "поиск клиентов",
        "каналы общения",
        "технология продажи",
        "просчет цены"
    ]
}
